{
  "version": "7",
  "dialect": "postgresql",
  "entries": [
    {
      "idx": 0,
      "version": "7",
      "when": 1724760432752,
      "tag": "0000_regular_ken_ellis",
      "breakpoints": true
    },
    {
      "idx": 1,
      "version": "7",
      "when": 1724844803859,
      "tag": "0001_hesitant_slyde",
      "breakpoints": true
    },
    {
      "idx": 2,
      "version": "7",
      "when": 1724844911050,
      "tag": "0002_lying_killraven",
      "breakpoints": true
    },
    {
      "idx": 3,
      "version": "7",
      "when": 1724845099657,
      "tag": "0003_equal_stardust",
      "breakpoints": true
    },
    {
      "idx": 4,
      "version": "7",
      "when": 1724868714378,
      "tag": "0004_omniscient_silk_fever",
      "breakpoints": true
    },
    {
      "idx": 5,
      "version": "7",
      "when": 1724904905778,
      "tag": "0005_wooden_kabuki",
      "breakpoints": true
    }
  ]
}